coppice-0.2.0.dist-info/METADATA
coppice-0.2.0.dist-info/WHEEL
coppice-0.2.0.dist-info/entry_points.txt
coppice-0.2.0.dist-info/license_files/LICENSE
coppice/scripts/__init__.py
coppice/scripts/cli.py
coppice/__init__.py
coppice/_coppice.cpython-311-arm-linux-gnueabihf.so
coppice-0.2.0.dist-info/RECORD
